gpio_task3/rtl/gpio_ip.v
module gpio_ip (
    input  wire clk,
    input  wire rst_n,

    input  wire wr_en,
    input  wire rd_en,
    input  wire [3:0] addr,
    input  wire [31:0] wdata,
    output reg  [31:0] rdata,

    input  wire [31:0] gpio_in,
    output wire [31:0] gpio_out
);
reg [31:0] gpio_data;
reg [31:0] gpio_dir;
reg [31:0] gpio_read;
localparam ADDR_DATA = 4'h0;
localparam ADDR_DIR  = 4'h4;
localparam ADDR_READ = 4'h8;
always @(posedge clk or negedge rst_n) begin
    if (!rst_n) begin
        gpio_data <= 32'b0;
        gpio_dir  <= 32'b0;
    end else if (wr_en) begin
        case (addr)
            ADDR_DATA: gpio_data <= wdata;
            ADDR_DIR : gpio_dir  <= wdata;
        endcase
    end
end
assign gpio_out = gpio_data & gpio_dir;
integer i;

always @(*) begin
    for (i = 0; i < 32; i = i + 1) begin
        if (gpio_dir[i])
            gpio_read[i] = gpio_data[i];
        else
            gpio_read[i] = gpio_in[i];
    end
end
always @(*) begin
    if (rd_en) begin
        case (addr)
            ADDR_DATA: rdata = gpio_data;
            ADDR_DIR : rdata = gpio_dir;
            ADDR_READ: rdata = gpio_read;
            default  : rdata = 32'b0;
        endcase
    end else begin
        rdata = 32'b0;
    end
end
endmodule

gpio_task3/tb/gpio_tb.v
module gpio_tb;

    reg clk;
    reg rst_n;
    reg wr_en;
    reg rd_en;
    reg [3:0] addr;
    reg [31:0] wdata;
    wire [31:0] rdata;

    reg [31:0] gpio_in;
    wire [31:0] gpio_out;

    // DUT
    gpio_ip uut (
        .clk(clk),
        .rst_n(rst_n),
        .wr_en(wr_en),
        .rd_en(rd_en),
        .addr(addr),
        .wdata(wdata),
        .rdata(rdata),
        .gpio_in(gpio_in),
        .gpio_out(gpio_out)
    );

    // Clock generation
    always #5 clk = ~clk;

    initial begin
        $dumpfile("gpio.vcd");
        $dumpvars(0, gpio_tb);

        clk = 0;
        rst_n = 0;
        wr_en = 0;
        rd_en = 0;
        addr = 0;
        wdata = 0;
        gpio_in = 32'hAAAA_AAAA;

        // Reset
        #10 rst_n = 1;

        // -----------------------------
        // TEST 1: Set direction (lower 8 bits output)
        // -----------------------------
        #10;
        wr_en = 1;
        addr = 4'h4;   // DIR
        wdata = 32'h000000FF;
        #10 wr_en = 0;

        // -----------------------------
        // TEST 2: Write DATA
        // -----------------------------
        #10;
        wr_en = 1;
        addr = 4'h0;   // DATA
        wdata = 32'hA5A5A5A5;
        #10 wr_en = 0;

        // -----------------------------
        // TEST 3: Read DATA
        // -----------------------------
        #10;
        rd_en = 1;
        addr = 4'h0;
        #10 rd_en = 0;

        // -----------------------------
        // TEST 4: Read DIR
        // -----------------------------
        #10;
        rd_en = 1;
        addr = 4'h4;
        #10 rd_en = 0;

        // -----------------------------
        // TEST 5: Read GPIO_READ
        // -----------------------------
        #10;
        rd_en = 1;
        addr = 4'h8;
        #10 rd_en = 0;

        // -----------------------------
        // Change input values
        // -----------------------------
        #10;
        gpio_in = 32'hFFFF0000;

        #10;
        rd_en = 1;
        addr = 4'h8;
        #10 rd_en = 0;

        #50 $finish;
    end

endmodule

gpio_task3/gpio.vcd
$date
	Tue Mar 31 16:56:06 2026
$end
$version
	Icarus Verilog
$end
$timescale
	1s
$end
$scope module gpio_tb $end
$var wire 32 ! rdata [31:0] $end
$var wire 32 " gpio_out [31:0] $end
$var reg 4 # addr [3:0] $end
$var reg 1 $ clk $end
$var reg 32 % gpio_in [31:0] $end
$var reg 1 & rd_en $end
$var reg 1 ' rst_n $end
$var reg 32 ( wdata [31:0] $end
$var reg 1 ) wr_en $end
$scope module uut $end
$var wire 4 * addr [3:0] $end
$var wire 1 $ clk $end
$var wire 32 + gpio_in [31:0] $end
$var wire 32 , gpio_out [31:0] $end
$var wire 1 & rd_en $end
$var wire 1 ' rst_n $end
$var wire 32 - wdata [31:0] $end
$var wire 1 ) wr_en $end
$var reg 32 . gpio_data [31:0] $end
$var reg 32 / gpio_dir [31:0] $end
$var reg 32 0 gpio_read [31:0] $end
$var reg 32 1 rdata [31:0] $end
$var integer 32 2 i [31:0] $end
$upscope $end
$upscope $end
$enddefinitions $end
#0
$dumpvars
b100000 2
b0 1
b10101010101010101010101010101010 0
b0 /
b0 .
b0 -
b0 ,
b10101010101010101010101010101010 +
b0 *
0)
b0 (
0'
0&
b10101010101010101010101010101010 %
0$
b0 #
b0 "
b0 !
$end
#5
1$
#10
0$
1'
#15
1$
#20
0$
b11111111 (
b11111111 -
b100 #
b100 *
1)
#25
b10101010101010101010101000000000 0
b100000 2
b11111111 /
1$
#30
0$
0)
#35
1$
#40
0$
b10100101101001011010010110100101 (
b10100101101001011010010110100101 -
b0 #
b0 *
1)
#45
b10101010101010101010101010100101 0
b100000 2
b10100101 "
b10100101 ,
b10100101101001011010010110100101 .
1$
#50
0$
0)
#55
1$
#60
b10100101101001011010010110100101 !
b10100101101001011010010110100101 1
0$
1&
#65
1$
#70
b0 !
b0 1
0$
0&
#75
1$
#80
b11111111 !
b11111111 1
0$
b100 #
b100 *
1&
#85
1$
#90
b0 !
b0 1
0$
0&
#95
1$
#100
b10101010101010101010101010100101 !
b10101010101010101010101010100101 1
0$
b1000 #
b1000 *
1&
#105
1$
#110
b0 !
b0 1
0$
0&
#115
1$
#120
b11111111111111110000000010100101 0
b100000 2
0$
b11111111111111110000000000000000 %
b11111111111111110000000000000000 +
#125
1$
#130
b11111111111111110000000010100101 !
b11111111111111110000000010100101 1
0$
1&
#135
1$
#140
b0 !
b0 1
0$
0&
